{"type":"PR","pr":{"number":3,"head":"b151dfc80ad2546972c30dbe628bbb82435e1740"},"user":"long.luong","status":"pending_publish","branch":"cms/2018-03-15-hôm-nay-mai-linh-hợp-tác-bán-vé-trên-vxr","collection":"tin-tuc","title":"Hôm nay Mai Linh hợp tác bán vé trên VXR","description":"No Description!","objects":{"entry":{"path":"content/tin-tuc/2018-03-15-hôm-nay-mai-linh-hợp-tác-bán-vé-trên-vxr.md","sha":"88ff52f18f4b511965017a7113b935be41852cc3"},"files":[]},"timeStamp":"2018-03-14T17:08:17.203Z"}